nomad_simulation_apps/__init__.py
nomad_simulation_apps/apps/__init__.py
nomad_simulation_apps/apps/alexandria_app.py
nomad_simulation_apps/apps/alexandria_dashboard.yaml
nomad_simulation_apps-0.1.2.dist-info/licenses/LICENSE
nomad_simulation_apps-0.1.2.dist-info/METADATA
nomad_simulation_apps-0.1.2.dist-info/WHEEL
nomad_simulation_apps-0.1.2.dist-info/entry_points.txt
nomad_simulation_apps-0.1.2.dist-info/top_level.txt
nomad_simulation_apps-0.1.2.dist-info/RECORD
