Metadata-Version: 2.4
Name: nomad-simulation-apps
Version: 0.1.2
Summary: A repository for housing NOMAD's collection of simulation app plugins.
Author-email: Martin Kuban <kuban@physik.hu-berlin.de>
Maintainer-email: Martin Kuban <kuban@physik.hu-berlin.de>
License: 
Project-URL: Repository, https://github.com/FAIRmat-NFDI/nomad-app-plugins-simulation
Project-URL: Documentation, https://fairmat-nfdi.github.io/nomad-app-plugins-simulation/
Classifier: Intended Audience :: Developers
Classifier: Operating System :: OS Independent
Classifier: Programming Language :: Python
Classifier: Programming Language :: Python :: 3.9
Classifier: Programming Language :: Python :: 3.10
Classifier: Programming Language :: Python :: 3.11
Classifier: Programming Language :: Python :: 3.12
Classifier: License :: OSI Approved :: Apache Software License
Requires-Python: >=3.9
License-File: LICENSE
Requires-Dist: nomad-lab>=1.3.0
Requires-Dist: python-magic-bin; sys_platform == "win32"
Provides-Extra: dev
Requires-Dist: ruff; extra == "dev"
Requires-Dist: pytest; extra == "dev"
Requires-Dist: structlog; extra == "dev"
Dynamic: license-file
